tagmaster/__init__.py
tagmaster/classification_client.py
tagmaster_python-1.0.7.dist-info/licenses/LICENSE
tagmaster_python-1.0.7.dist-info/METADATA
tagmaster_python-1.0.7.dist-info/WHEEL
tagmaster_python-1.0.7.dist-info/top_level.txt
tagmaster_python-1.0.7.dist-info/RECORD
