Metadata-Version: 2.4
Name: tagmaster-python
Version: 1.0.7
Summary: A comprehensive Python client for the Tagmaster classification API with project management, category management, AI classification, and analytics
Home-page: https://github.com/tagmaster/tagmaster-python
Author: Tagmaster
Author-email: Tagmaster <support@tagmaster.com>
Maintainer-email: Tagmaster <support@tagmaster.com>
License: MIT
Project-URL: Homepage, https://github.com/tagmaster/tagmaster-python
Project-URL: Documentation, https://github.com/tagmaster/tagmaster-python#readme
Project-URL: Repository, https://github.com/tagmaster/tagmaster-python
Project-URL: Bug Tracker, https://github.com/tagmaster/tagmaster-python/issues
Keywords: tagmaster,classification,api,client,text-analysis,nlp,project-management,category-management,analytics,csv-import-export
Classifier: Development Status :: 4 - Beta
Classifier: Intended Audience :: Developers
Classifier: License :: OSI Approved :: MIT License
Classifier: Operating System :: OS Independent
Classifier: Programming Language :: Python :: 3
Classifier: Programming Language :: Python :: 3.7
Classifier: Programming Language :: Python :: 3.8
Classifier: Programming Language :: Python :: 3.9
Classifier: Programming Language :: Python :: 3.10
Classifier: Programming Language :: Python :: 3.11
Classifier: Programming Language :: Python :: 3.12
Classifier: Topic :: Software Development :: Libraries :: Python Modules
Classifier: Topic :: Text Processing :: Linguistic
Classifier: Topic :: Scientific/Engineering :: Artificial Intelligence
Requires-Python: >=3.7
License-File: LICENSE
Requires-Dist: requests>=2.31.0
Provides-Extra: dev
Requires-Dist: pytest>=6.0; extra == "dev"
Requires-Dist: pytest-cov>=2.0; extra == "dev"
Requires-Dist: black>=21.0; extra == "dev"
Requires-Dist: flake8>=3.8; extra == "dev"
Requires-Dist: mypy>=0.800; extra == "dev"
Dynamic: author
Dynamic: home-page
Dynamic: license-file
Dynamic: requires-python
